whatsapp_cloud_api_sdk-1.0.0.dist-info/licenses/LICENSE
whatsappcloudapi/__init__.py
whatsappcloudapi/api_helper.py
whatsappcloudapi/configuration.py
whatsappcloudapi/whatsappcloudapi_client.py
whatsappcloudapi/controllers/__init__.py
whatsappcloudapi/controllers/analytics_controller.py
whatsappcloudapi/controllers/base_controller.py
whatsappcloudapi/controllers/billing_controller.py
whatsappcloudapi/controllers/block_users_controller.py
whatsappcloudapi/controllers/business_compliance_controller.py
whatsappcloudapi/controllers/business_portfolio_controller.py
whatsappcloudapi/controllers/business_profiles_controller.py
whatsappcloudapi/controllers/commerce_settings_controller.py
whatsappcloudapi/controllers/create_flow_controller.py
whatsappcloudapi/controllers/examples_controller.py
whatsappcloudapi/controllers/get_endpoint_metrics_controller.py
whatsappcloudapi/controllers/get_started_controller.py
whatsappcloudapi/controllers/media_controller.py
whatsappcloudapi/controllers/messages_controller.py
whatsappcloudapi/controllers/on_prem_account_migration_controller.py
whatsappcloudapi/controllers/payments_apiin_controller.py
whatsappcloudapi/controllers/payments_apisg_controller.py
whatsappcloudapi/controllers/phone_numbers_controller.py
whatsappcloudapi/controllers/qr_codes_controller.py
whatsappcloudapi/controllers/registration_controller.py
whatsappcloudapi/controllers/send_flow_controller.py
whatsappcloudapi/controllers/setup_endpoint_encryption_controller.py
whatsappcloudapi/controllers/templates_controller.py
whatsappcloudapi/controllers/typing_indicators_controller.py
whatsappcloudapi/controllers/update_flow_controller.py
whatsappcloudapi/controllers/webhook_payload_reference_controller.py
whatsappcloudapi/controllers/webhook_subscriptions_controller.py
whatsappcloudapi/controllers/whats_app_business_accounts_wab_as_controller.py
whatsappcloudapi/exceptions/__init__.py
whatsappcloudapi/exceptions/api_exception.py
whatsappcloudapi/http/__init__.py
whatsappcloudapi/http/http_call_back.py
whatsapp_cloud_api_sdk-1.0.0.dist-info/METADATA
whatsapp_cloud_api_sdk-1.0.0.dist-info/WHEEL
whatsapp_cloud_api_sdk-1.0.0.dist-info/top_level.txt
whatsapp_cloud_api_sdk-1.0.0.dist-info/RECORD
